{"ScheduleID":4159,"Day":9,"Month":1,"Year":2023,"TimeBlockDTO":{"TimeblockID":9,"StartingTime":"08:00:00","EndingTime":"09:00:00"},"EmployeeDTO":{"EmployeeID":3,"Role":"Office","Password":"WZRHGrsBESr8wYFZ9sx0tPURuZgG2lmzyvWpwXPKz8U=","UnavailabilityDays":15,"FirstName":"Delila","LastName":"Garritley","Email":"3@3","Phone":"+86 622 636 7956","Address":"808 Evergreen Trail"},"TaskDTO":{"TaskID":92,"Name":"Cleaning","AnimalDTO":null,"HabitatDTO":{"HabitatID":17,"Name":"Wetlands","Capacity":10,"ZoneDTO":{"ZoneID":6,"Name":"Europe","Capacity":30}}}}